{
  "lastUpdated": "Apr 1, 2026",
  "projects": [
    {"id":1,"name":"Validate Karbon_entities Table","pillar":"modeling","owners":["Ervina","Daniel"],"status":"In Progress","priority":"P1","stakeholder":"","due":"","dependencies":"Foundational","tier":null,"notes":"Cleared ~5k records. Daniel re-running analysis. Waiting to get confirmation on if we can activate the syncing of certain contact types from Karbon to NetSuite. Also waiting for Daniel to get back in office Mon 3/2.","lastModified":"Mar 10, 2026"},
    {"id":2,"name":"Update Core client_subsidiary Model","pillar":"modeling","owners":["Ervina","Daniel"],"status":"In Progress","priority":"P1","stakeholder":"","due":"","dependencies":"Depends on #1","tier":null,"notes":"Confirmed table logic with Tyson. The table should increase by rows for every client_subsidiary relationship. Additionally we will bring in the leadership_position_3 and leadership_position_4 fields from kpi_dimn_client to represent the CAS client owner and manager. We are holding off on adding operational logic around forcing the use of client owner/manager fields and CAS fields between office 3 and local offices.","lastModified":"Feb 26, 2026"},
    {"id":4,"name":"Create Validation Process","pillar":"gov","owners":["Ervina"],"status":"","priority":"Future","stakeholder":"","due":"","dependencies":"None","tier":null,"notes":"Future orchestration project. Catch inactive users, email changes, RLS integrity.","lastModified":"Feb 25, 2026"},
    {"id":5,"name":"Monthly Tie-Out to Financials","pillar":"gov","owners":["Ervina"],"status":"","priority":"P1","stakeholder":"CFO","due":"","dependencies":"Depends on #4","tier":null,"notes":"Reconcile Power BI vs. financials monthly","lastModified":"Feb 25, 2026"},
    {"id":6,"name":"Full WIP Report w/ Automated Flags","pillar":"reporting","owners":["Ervina"],"status":"","priority":"P1","stakeholder":"CFO","due":"","dependencies":"Depends on #1, #2","tier":null,"notes":"Monthly review workflow with flag logic","lastModified":"Feb 25, 2026"},
    {"id":7,"name":"Align HR, IT & Data on Employee Groups","pillar":"intake","owners":["Ervina"],"status":"","priority":"Future","stakeholder":"","due":"","dependencies":"None","tier":null,"notes":"Future project. Define groupings, update DIM_RLS.","lastModified":"Feb 25, 2026"},
    {"id":8,"name":"Move Power BI Access to IT/HR","pillar":"gov","owners":["Ervina"],"status":"","priority":"P2","stakeholder":"","due":"","dependencies":"Depends on #7","tier":null,"notes":"Remove manual Security Group bottleneck","lastModified":"Feb 25, 2026"},
    {"id":9,"name":"Clean Up Snowflake Roles & Permissions","pillar":"gov","owners":["Ervina"],"status":"","priority":"P2","stakeholder":"","due":"","dependencies":"None","tier":null,"notes":"Unblock pending access requests","lastModified":"Feb 25, 2026"},
    {"id":10,"name":"Integrate Paylocity via Fivetran","pillar":"intake","owners":["Ervina"],"status":"","priority":"P2","stakeholder":"","due":"","dependencies":"None","tier":2,"notes":"Manual weekly upload (interim)","lastModified":"Feb 27, 2026"},
    {"id":11,"name":"HDI Timekeeping Data - Architecture Design","pillar":"modeling","owners":["Ervina"],"status":"","priority":"P2","stakeholder":"CFO","due":"","dependencies":"None","tier":null,"notes":"Designing architecture for HDI timekeeping data. Abdulrahman completed HDI for 5 offices.","lastModified":"Feb 26, 2026"},
    {"id":12,"name":"Daily Production by Office vs. PY & Forecast","pillar":"reporting","owners":["Ervina"],"status":"","priority":"P2","stakeholder":"CFO","due":"","dependencies":"Depends on #3","tier":null,"notes":"Daily output vs. prior year and forecast","lastModified":"Feb 25, 2026"},
    {"id":14,"name":"Implement Orchestration Tooling","pillar":"gov","owners":["Ervina"],"status":"","priority":"P2","stakeholder":"","due":"","dependencies":"None","tier":null,"notes":"Prevent silent Power BI failures","lastModified":"Feb 25, 2026"},
    {"id":16,"name":"Exception Report for Office Admins","pillar":"reporting","owners":["Abdulrahman"],"status":"Planned","priority":"P2","stakeholder":"","due":"","dependencies":"None","tier":null,"notes":"Push data quality ownership to source","lastModified":"Feb 27, 2026"},
    {"id":17,"name":"Aged WIP by Office","pillar":"reporting","owners":["Ervina"],"status":"","priority":"P3","stakeholder":"CFO","due":"","dependencies":"Depends on #1, #2","tier":null,"notes":"WIP aging model per office","lastModified":"Feb 25, 2026"},
    {"id":18,"name":"New Churn Model (Lost \u2192 WIP)","pillar":"modeling","owners":["Ervina","Daniel"],"status":"","priority":"P3","stakeholder":"","due":"","dependencies":"Depends on #1, #2","tier":null,"notes":"Cross-ref Karbon work against 'lost' labels","lastModified":"Feb 25, 2026"},
    {"id":19,"name":"TTM & YTD Churn Models","pillar":"modeling","owners":["Ervina","Daniel"],"status":"","priority":"P3","stakeholder":"","due":"","dependencies":"Depends on #1, #2, #16","tier":null,"notes":"Stable foundation required","lastModified":"Feb 25, 2026"},
    {"id":20,"name":"Update Median Pricing Formula","pillar":"reporting","owners":["Ervina"],"status":"","priority":"P3","stakeholder":"","due":"","dependencies":"None","tier":null,"notes":"New KPI reporting","lastModified":"Feb 25, 2026"},
    {"id":21,"name":"Update Executive Dashboard","pillar":"reporting","owners":["Ervina"],"status":"In Progress","priority":"P3","stakeholder":"","due":"This week","dependencies":"Depends on #3","tier":null,"notes":"Update Ops Manager filters. Restructuring YoY.","lastModified":"Feb 25, 2026"},
    {"id":22,"name":"New A/R Filters for Finance","pillar":"intake","owners":["Ervina"],"status":"","priority":"P3","stakeholder":"","due":"","dependencies":"None","tier":null,"notes":"","lastModified":"Feb 25, 2026"},
    {"id":24,"name":"Talent Acquisition - Candidate Pipeline Tool","pillar":"ai","owners":["Abdulrahman"],"status":"On Hold","priority":"Pipeline","stakeholder":"","due":"","dependencies":"None","tier":null,"notes":"TA tool that organizes all internal datasets and documentation to give the TA team a list of possible candidates when a new role is added to coda. This is sourced from candidates who previously applied via Paylocity and/or resumes that the TA team collected and is stored in their sharepoint.","lastModified":"Mar 10, 2026"},
    {"id":25,"name":"Compliance Request","pillar":"ai","owners":["Abdulrahman"],"status":"On Hold","priority":"Pipeline","stakeholder":"","due":"","dependencies":"None","tier":null,"notes":"","lastModified":"Mar 10, 2026"},
    {"id":27,"name":"CY PY Bar Graph - Gross Production","pillar":"reporting","owners":["Abdulrahman"],"status":"","priority":"P2","stakeholder":"","due":"","dependencies":"None","tier":null,"notes":"Similar to revenue by client owner report","lastModified":"Feb 27, 2026"},
    {"id":28,"name":"Add Paylocity Roles to Billable Hours","pillar":"reporting","owners":["Abdulrahman"],"status":"","priority":"P2","stakeholder":"","due":"","dependencies":"None","tier":null,"notes":"Verify dbt column (user_account table), add if missing, update PowerBI","lastModified":"Feb 27, 2026"},
    {"id":29,"name":"HDI Toggle in PowerBI","pillar":"reporting","owners":["Abdulrahman"],"status":"","priority":"P2","stakeholder":"","due":"","dependencies":"None","tier":null,"notes":"Add HDI toggle to PowerBI reporting","lastModified":"Feb 27, 2026"},
    {"id":30,"name":"Executive Cohort Details","pillar":"reporting","owners":["Ervina"],"status":"","priority":"P2","stakeholder":"","due":"","dependencies":"None","tier":null,"notes":"PowerBI reporting updates","lastModified":"Feb 25, 2026"},
    {"id":31,"name":"Separate Team KPI from Book of Business","pillar":"reporting","owners":["Ervina"],"status":"","priority":"Future","stakeholder":"","due":"","dependencies":"None","tier":null,"notes":"KPI Beta App, future consideration","lastModified":"Feb 25, 2026"},
    {"id":32,"name":"Introduce Target Metrics in Reporting","pillar":"reporting","owners":["Ervina"],"status":"","priority":"Future","stakeholder":"","due":"","dependencies":"None","tier":null,"notes":"Across different reports, future consideration","lastModified":"Feb 25, 2026"},
    {"id":33,"name":"HDI Timekeeping Data - Upload","pillar":"intake","owners":["Abdulrahman"],"status":"","priority":"P2","stakeholder":"","due":"","dependencies":"Depends on #11","tier":null,"notes":"Upload all timekeeping data for previous HDI offices. Waiting on Ervina to finish Time Data Architecture.","lastModified":"Feb 27, 2026"},
    {"id":42,"name":"Update Karbon Status Mapping Table","pillar":"modeling","owners":["Abdulrahman"],"status":"On Hold","priority":"P2","stakeholder":"","due":"","dependencies":"None","tier":null,"notes":"Request from Mark. Bayshore Advisors - Santa Cruz office. Update in Snowflake.","lastModified":"Mar 10, 2026"},
    {"id":43,"name":"PowerBI Access Issue - Jeff Dredge","pillar":"reporting","owners":["Abdulrahman"],"status":"Cancelled","priority":"P1","stakeholder":"Jeff Dredge","due":"","dependencies":"None","tier":null,"notes":"Jeff cannot see any revenue in PowerBI. Investigate access issue. Access looks okay. Waiting for Jeff to send screenshots of the issue. Never heard back from Jeff Dredge.","lastModified":"Mar 17, 2026"},
    {"id":44,"name":"Create Data Ticketing System","pillar":"gov","owners":["Abdulrahman"],"status":"On Hold","priority":"P2","stakeholder":"","due":"","dependencies":"None","tier":null,"notes":"Formalize request intake so data requests aren't coming through Teams and getting lost.","lastModified":"Mar 10, 2026"},
    {"id":47,"name":"FiveTran Netsuite2.com Source Migration","pillar":"gov","owners":["Ervina"],"status":"In Progress","priority":"P1","stakeholder":"","due":"","dependencies":"None","tier":4,"notes":"Netsuite will eliminate the previous data source and move to netsuite2. We will have to review and plan the migration of our source data ahead of time so nothing breaks when the source is changed.","lastModified":"Feb 26, 2026"},
    {"id":48,"name":"Office Mapping - Hulquist","pillar":"intake","owners":["Abdulrahman"],"status":"","priority":"P2","stakeholder":"","due":"","dependencies":"None","tier":2,"notes":"Connect the new acquisition's netsuite instance to the karbon instance in our database. Confirm the NetSuite database contains the office and note the Subsidiary Name and Subsidiary ID. Confirm the KPI database contains the office and note the Account Name and Account ID. (This requires reaching out to Karbon to ensure they add the office). Finally confirm HR has created the new Department Description. When all of these conditions exist and are met, we can connect the data","lastModified":"Feb 27, 2026"},
    {"id":49,"name":"Office Mapping - BA, Inc","pillar":"intake","owners":["Abdulrahman"],"status":"","priority":"P2","stakeholder":"","due":"","dependencies":"None","tier":2,"notes":"Connect the new acquisition's netsuite instance to the karbon instance in our database. Confirm the NetSuite database contains the office and note the Subsidiary Name and Subsidiary ID. Confirm the KPI database contains the office and note the Account Name and Account ID. (This requires reaching out to Karbon to ensure they add the office). Finally confirm HR has created the new Department Description. When all of these conditions exist and are met, we can connect the data","lastModified":"Feb 27, 2026"},
    {"id":50,"name":"Office Mapping - St.Clair","pillar":"intake","owners":["Abdulrahman"],"status":"","priority":"P2","stakeholder":"","due":"","dependencies":"None","tier":2,"notes":"Connect the new acquisition's netsuite instance to the karbon instance in our database. Confirm the NetSuite database contains the office and note the Subsidiary Name and Subsidiary ID. Confirm the KPI database contains the office and note the Account Name and Account ID. (This requires reaching out to Karbon to ensure they add the office). Finally confirm HR has created the new Department Description. When all of these conditions exist and are met, we can connect the data","lastModified":"Feb 27, 2026"},
    {"id":51,"name":"Office Mapping - Smeriglio","pillar":"intake","owners":["Abdulrahman"],"status":"","priority":"P2","stakeholder":"","due":"","dependencies":"None","tier":2,"notes":"Connect the new acquisition's netsuite instance to the karbon instance in our database. Confirm the NetSuite database contains the office and note the Subsidiary Name and Subsidiary ID. Confirm the KPI database contains the office and note the Account Name and Account ID. (This requires reaching out to Karbon to ensure they add the office). Finally confirm HR has created the new Department Description. When all of these conditions exist and are met, we can connect the data","lastModified":"Feb 27, 2026"},
    {"id":52,"name":"Engagement Letter Signatures","pillar":"reporting","owners":["Ervina"],"status":"In Progress","priority":"P2","stakeholder":"Tyson","due":"","dependencies":"None","tier":1,"notes":"Show project by client and client owner and then getting the list of Karbon task names that are either checked or not and showing that.","lastModified":"Mar 10, 2026"},
    {"id":54,"name":"Platform Connect Data Analysis Request","pillar":"reporting","owners":["Abdulrahman"],"status":"Waiting","priority":"P2","stakeholder":"Mike, Chase","due":"","dependencies":"None","tier":null,"notes":"Analyze capacity planning / hours worked within certain service line segments across all of Platform to see where there are areas to consolidate service lines and mitigate key-person risk. Would need all Platform offices using Karbon, that were tracking work from 1/1/25 to 12/31/25. Team message includes data points requested.","lastModified":"Mar 10, 2026"},
    {"id":61,"name":"Bolton Acquisition Tool","pillar":"ai","owners":["Abdulrahman"],"status":"On Hold","priority":"Pipeline","stakeholder":"Corp Dev Team","due":"","dependencies":"None","tier":null,"notes":"","lastModified":"Mar 10, 2026"},
    {"id":60,"name":"Update Madison Street HDI","pillar":"intake","owners":["Abdulrahman"],"status":"In Progress","priority":"P2","stakeholder":"Tyson","due":"","dependencies":"None","tier":null,"notes":"","lastModified":"Mar 10, 2026"},
    {"id":59,"name":"Talent Acquisition - Automated Coordinator Workflow","pillar":"ai","owners":["Abdulrahman"],"status":"On Hold","priority":"Pipeline","stakeholder":"Chris Schafer","due":"","dependencies":"None","tier":4,"notes":"A webapp that replaces the coordinator role on the TA team. It preps the interviewer, schedules, and coordinates candidate interview process.","lastModified":"Mar 10, 2026"},
    {"id":58,"name":"Review Master - HR Tool","pillar":"ai","owners":["Abdulrahman"],"status":"In Progress","priority":"P1","stakeholder":"Tyson","due":"","dependencies":"None","tier":4,"notes":"HR Tool that streamlines annual comp cycle. An Infrastructure request was made and sent to IT and Security. We're waiting on the 7 requirements listed in the Inf. Request. See doc for details. Deploying the tool can't be done until requests are fulfilled. The hierarchy structure has been completed, the planning and md file is done, and currently working on publishing a local page with the dummy data to test the first version of the tool.","lastModified":"Mar 10, 2026"},
    {"id":57,"name":"Add WIP Breakout Filter to KPI","pillar":"reporting","owners":["Abdulrahman"],"status":"In Progress","priority":"P2","stakeholder":"Amber","due":"","dependencies":"None","tier":null,"notes":"KPI Report includes all billing types and this is inconsistent compared to the WIP and RLZ report because there we only show T&M/Fixed Billing Type WIP. To add clarity we will include a billing type WIP filter on the KPI PowerBI report.","lastModified":"Mar 10, 2026"},
    {"id":62,"name":"Update Time and Billing HDI for Keystone-O","pillar":"intake","owners":["Abdulrahman"],"status":"In Progress","priority":"P1","stakeholder":"Tyson","due":"","dependencies":"None","tier":null,"notes":"Reached out to the Admin.","lastModified":"Mar 10, 2026"},
    {"id":63,"name":"Realization Dashboard","pillar":"reporting","owners":["Ervina"],"status":"","priority":"P1","stakeholder":"Tyson","due":"","dependencies":"None","tier":3,"notes":"Build a new Realization Dashboard in Power BI for COO Tyson.","lastModified":"Apr 1, 2026"}
  ],
  "completed": [
    {"id":1,"name":"Historical Data Integration - 5 Offices","subtitle":"ASG, Pottsville, Greencoast, Walpole, Santa Cruz","owner":"Abdulrahman","pillar":"modeling","date":"Feb 23","tier":null,"impact":"Uploaded tables to Snowflake, added to dbt models, published in Power BI. Full pipeline delivery.","lastModified":"Feb 23, 2026"},
    {"id":2,"name":"Added Karbon Statuses to Snowflake for Brian","subtitle":"","owner":"Abdulrahman","pillar":"intake","date":"Feb 18","tier":null,"impact":"Loaded Karbon status data into Snowflake, published for reporting.","lastModified":"Feb 18, 2026"},
    {"id":3,"name":"Added Karbon Statuses to Snowflake for Mark/Tyson Colledge","subtitle":"","owner":"Abdulrahman","pillar":"intake","date":"Feb 18","tier":null,"impact":"Loaded Karbon status data for Colledge offices.","lastModified":"Feb 18, 2026"},
    {"id":4,"name":"Custom Data Request for Chase - Two Offices","subtitle":"","owner":"Abdulrahman","pillar":"intake","date":"Feb 18","tier":null,"impact":"Custom data extraction and delivery for two offices.","lastModified":"Feb 18, 2026"},
    {"id":5,"name":"dim_date Table","subtitle":"","owner":"Ervina","pillar":"modeling","date":"Feb 24","tier":null,"impact":"Created in Snowflake via Initial Table Creation Notebook. Does not need to be run again.","lastModified":"Feb 24, 2026"},
    {"id":6,"name":"Ryan's Data Request (PDF IDs)","subtitle":"","owner":"Abdulrahman","pillar":"intake","date":"Feb 24","tier":null,"impact":"CFO data request. IDs in PDF format.","lastModified":"Feb 24, 2026"},
    {"id":7,"name":"PowerBI Bug: Sarah Lippled Client Owner (Amber)","subtitle":"","owner":"Abdulrahman","pillar":"modeling","date":"Feb 26","tier":null,"impact":"Sarah Lippled showing as client_owner on KPI report under Meridian, but she is not in that firm. Root cause: mismatching keys between the vw_fact_sales_reward table and the dim_subsidiary table because the PowerBI semantic model was pulling dim_subsidiary from sandbox but the actual vw_fact_sales_reward table was internally joining to dim_subsidiary in analytics causing mismatched keys.","lastModified":"Feb 26, 2026"},
    {"id":8,"name":"Office Prospecting Tool","subtitle":"","owner":"Abdulrahman","pillar":"ai","date":"Feb 26","tier":null,"impact":"AI tool for Noah (Corp Dev). Generates list of acquirable offices by state, filtering noisy data.","lastModified":"Feb 26, 2026"},
    {"id":9,"name":"Pathlight Earnout Analysis","subtitle":"","owner":"Ervina","pillar":"intake","date":"Feb 26","tier":null,"impact":"Explained missing invoices in earnout statement.","lastModified":"Feb 26, 2026"},
    {"id":10,"name":"Data Request for Chase - Karbon Work Types, Task Types & Roles","subtitle":"","owner":"Abdulrahman","pillar":"intake","date":"Mar 4","stakeholder":"Chase","tier":null,"impact":"Sent table of all work types, task types, and roles across all offices in the Karbon instance.","lastModified":"Mar 4, 2026"},
    {"id":11,"name":"PowerBI Bug: A/R Report Refresh - DHS (Amber)","subtitle":"","owner":"Abdulrahman","pillar":"reporting","date":"Mar 6","stakeholder":"Amber","tier":null,"impact":"The issue was likely due to the Snowflake refresh errors that occurred in Notebooks","lastModified":"Mar 6, 2026"},
    {"id":12,"name":"PowerBI Bug: Mike Watters Incorrect Office (Amber)","subtitle":"","owner":"Abdulrahman","pillar":"reporting","date":"Mar 6","stakeholder":"Amber","tier":null,"impact":"Likely resolved with the same fix that resolved Sarah Lippold","lastModified":"Mar 6, 2026"},
    {"id":13,"name":"Karbon User Data Request","subtitle":"","owner":"Abdulrahman","pillar":"reporting","date":"Mar 10","stakeholder":"Mike","tier":null,"impact":"Pulled max last login date to capture users not active in Karbon.","lastModified":"Mar 10, 2026"},
    {"id":14,"name":"Client Owner Returns Data Request","subtitle":"","owner":"Abdulrahman","pillar":"reporting","date":"Mar 10","stakeholder":"Mike","tier":null,"impact":"Delivered returns count for John Bostwick in 2025 where he was the sole time-tracker, as a measure of client transition readiness and engagement of others in work.","lastModified":"Mar 10, 2026"},
    {"id":15,"name":"Data Request for Tyson - HDI Master Production File","subtitle":"","owner":"Abdulrahman","pillar":"intake","date":"Mar 10","stakeholder":"Tyson","tier":null,"impact":"Compiled all clean production data from HDI extracts into one master Excel file.","lastModified":"Mar 10, 2026"},
    {"id":16,"name":"Update Master Office Mapping","subtitle":"","owner":"Ervina","pillar":"modeling","date":"Mar 10","stakeholder":"","tier":null,"impact":"Updated dbt model with cohort details merged into subsidiary table. Built two lookup tables for NS <> KB office mapping in both directions at the stage level.","lastModified":"Mar 10, 2026"},
    {"id":17,"name":"Connect Sharepoint <> FiveTran","subtitle":"","owner":"Ervina","pillar":"gov","date":"Mar 10","stakeholder":"","tier":null,"impact":"Created a Sharepoint site to sync cohort details and HR department descriptions into FiveTran to eliminate manual process. Testing and adding permissions.","lastModified":"Mar 10, 2026"},
    {"id":18,"name":"PowerBI Bug: Brett M Contreras WIP (Amber)","subtitle":"","owner":"Abdulrahman","pillar":"reporting","date":"Mar 17","stakeholder":"Amber","tier":null,"impact":"Resolved WIP discrepancy showing $6.6k vs. actual $170 for Brett M Contreras client.","lastModified":"Mar 17, 2026"},
    {"id":19,"name":"PowerBI Bug: BC Athletics WIP (Amber)","subtitle":"","owner":"Abdulrahman","pillar":"reporting","date":"Mar 17","stakeholder":"Amber","tier":null,"impact":"Resolved WIP discrepancy for BC Athletics, same root cause as Brett M Contreras issue.","lastModified":"Mar 17, 2026"},
    {"id":20,"name":"PowerBI Bug: Negative Production - Meridian (Amber)","subtitle":"","owner":"Abdulrahman","pillar":"reporting","date":"Mar 17","stakeholder":"Amber","tier":null,"impact":"Investigated and explained negative production showing on Meridian in PowerBI.","lastModified":"Mar 17, 2026"},
    {"id":21,"name":"PowerBI Bug: Arkose Advisors A/R (Brian)","subtitle":"Michael & Tracey Moore","owner":"Abdulrahman","pillar":"reporting","date":"Mar 17","stakeholder":"Brian","tier":null,"impact":"Resolved negative $2,040 A/R balance discrepancy between PowerBI and NetSuite ($1,285 open balance).","lastModified":"Mar 17, 2026"},
    {"id":22,"name":"PowerBI Bug: WIP N/A - Jack C Wilder Admin Trust (Amber)","subtitle":"","owner":"Abdulrahman","pillar":"reporting","date":"Mar 17","stakeholder":"Amber","tier":null,"impact":"The WIP discrepancies were solved with the other ticket items. Regarding Client Owner stuff, we'll wait to deploy the new client_sub model before digging in.","lastModified":"Mar 17, 2026"}
  ],
  "changelog": [
    {"date": "Apr 1, 2026", "author": "Ervina", "action": "Added new project: Realization Dashboard (Power BI) for COO Tyson", "ref": "#63"},
    {"date": "Mar 17, 2026", "author": "Ervina", "action": "Added Change Log tab to tracker; updated collaboration setup for Abdulrahman", "ref": ""}
  ]
}
